MANIFEST.in
README.txt
license.txt
setup.py
Django_PeerReview.egg-info/PKG-INFO
Django_PeerReview.egg-info/SOURCES.txt
Django_PeerReview.egg-info/dependency_links.txt
Django_PeerReview.egg-info/not-zip-safe
Django_PeerReview.egg-info/requires.txt
Django_PeerReview.egg-info/top_level.txt
peerreview/__init__.py
peerreview/admin.py
peerreview/logic.py
peerreview/models.py
peerreview/tests.py
peerreview/urls.py
peerreview/views.py
peerreview/static/bootstrap/css/bootstrap-responsive.css
peerreview/static/bootstrap/css/bootstrap-responsive.min.css
peerreview/static/bootstrap/css/bootstrap.css
peerreview/static/bootstrap/css/bootstrap.min.css
peerreview/static/bootstrap/css/carousel.css
peerreview/static/bootstrap/css/prettify.css
peerreview/static/bootstrap/img/glyphicons-halflings-white.png
peerreview/static/bootstrap/img/glyphicons-halflings.png
peerreview/static/bootstrap/js/bootstrap-button.js
peerreview/static/bootstrap/js/bootstrap-carousel.js
peerreview/static/bootstrap/js/bootstrap-popover.js
peerreview/static/bootstrap/js/bootstrap-tooltip.js
peerreview/static/bootstrap/js/bootstrap-transition.js
peerreview/static/bootstrap/js/bootstrap.js
peerreview/static/bootstrap/js/bootstrap.min.js
peerreview/static/bootstrap/js/google-code-prettify/prettify.js
peerreview/templates/admin/peerreview/review/change_form.html
peerreview/templates/admin/peerreview/review/email_message.html
peerreview/templates/peerreview/items_list.html
peerreview/templates/peerreview/review_wizard.html
peerreview/templates/peerreview/frontend/base.html
peerreview/templates/peerreview/frontend/base.mobile.html
peerreview/templates/peerreview/frontend/index.html
peerreview/templates/peerreview/frontend/index.ipad.html
peerreview/templates/peerreview/frontend/index.mobile.html
peerreview/templates/peerreview/frontend/item_list.html
peerreview/templates/peerreview/frontend/item_list.ipad.html
peerreview/templates/peerreview/frontend/login.html
peerreview/templates/peerreview/frontend/review_item.html
peerreview/templatetags/__init__.py
peerreview/templatetags/review_tags.py