Metadata-Version: 1.0
Name: Django-PeerReview
Version: 0.1.0
Summary: Simple reusable app for management of peer review of arbitrary django models.
Home-page: https://bitbucket.org/weholt/django-peer-review
Author: Thomas Weholt
Author-email: thomas@weholt.org
License: Modified BSD
Keywords: peer review arbitrary django models
Platform: UNKNOWN
Classifier: Development Status :: 4 - Beta
Classifier: Intended Audience :: Developers
Classifier: Framework :: Django
Classifier: License :: OSI Approved :: BSD License
Classifier: Operating System :: OS Independent
Classifier: Programming Language :: Python
Classifier: Topic :: Database
